odoo/addons/stock_warehouse_flow_product_packaging/README.rst
odoo/addons/stock_warehouse_flow_product_packaging/__init__.py
odoo/addons/stock_warehouse_flow_product_packaging/__manifest__.py
odoo/addons/stock_warehouse_flow_product_packaging/i18n/stock_warehouse_flow_product_packaging.pot
odoo/addons/stock_warehouse_flow_product_packaging/models/__init__.py
odoo/addons/stock_warehouse_flow_product_packaging/models/stock_warehouse_flow.py
odoo/addons/stock_warehouse_flow_product_packaging/readme/CONTRIBUTORS.rst
odoo/addons/stock_warehouse_flow_product_packaging/readme/DESCRIPTION.rst
odoo/addons/stock_warehouse_flow_product_packaging/static/description/icon.png
odoo/addons/stock_warehouse_flow_product_packaging/static/description/index.html
odoo/addons/stock_warehouse_flow_product_packaging/tests/__init__.py
odoo/addons/stock_warehouse_flow_product_packaging/tests/test_warehouse_flow.py
odoo/addons/stock_warehouse_flow_product_packaging/views/stock_warehouse_flow.xml
odoo14_addon_stock_warehouse_flow_product_packaging-14.0.2.0.0.dist-info/METADATA
odoo14_addon_stock_warehouse_flow_product_packaging-14.0.2.0.0.dist-info/WHEEL
odoo14_addon_stock_warehouse_flow_product_packaging-14.0.2.0.0.dist-info/top_level.txt
odoo14_addon_stock_warehouse_flow_product_packaging-14.0.2.0.0.dist-info/RECORD
