Metadata-Version: 2.1
Name: odoo14-addon-stock-warehouse-flow-product-packaging
Version: 14.0.2.0.0
Summary: Configure packaging types on routing flows for stock moves
Home-page: https://github.com/OCA/wms
Author: MT Software, Odoo Community Association (OCA)
Author-email: support@odoo-community.org
License: AGPL-3
Platform: UNKNOWN
Classifier: Programming Language :: Python
Classifier: Framework :: Odoo
Classifier: Framework :: Odoo :: 14.0
Classifier: License :: OSI Approved :: GNU Affero General Public License v3
Classifier: Development Status :: 3 - Alpha
Requires-Python: >=3.6
Requires-Dist: odoo14-addon-product-packaging-type
Requires-Dist: odoo14-addon-stock-warehouse-flow
Requires-Dist: odoo (<14.1dev,>=14.0a)
